babe/__init__.py
babe-0.0.7.dist-info/LICENSE
babe-0.0.7.dist-info/METADATA
babe-0.0.7.dist-info/WHEEL
babe-0.0.7.dist-info/top_level.txt
babe-0.0.7.dist-info/RECORD
