Metadata-Version: 2.1
Name: babe
Version: 0.0.7
Summary: Data access and analysis of baby names statistics
Home-page: https://github.com/thorwhalen/babe
Author: Thor Whalen
License: mit
Platform: any
